ai_act_check/__init__.py
ai_act_check/cli.py
ai_act_check/public_drafter.py
ai_act_check/scanner.py
ai_act_check/data/risk_map.json
ai_act_check-2.0.1.dist-info/licenses/LICENSE
ai_act_check-2.0.1.dist-info/METADATA
ai_act_check-2.0.1.dist-info/WHEEL
ai_act_check-2.0.1.dist-info/entry_points.txt
ai_act_check-2.0.1.dist-info/top_level.txt
ai_act_check-2.0.1.dist-info/RECORD
