Metadata-Version: 2.4
Name: ai-act-check
Version: 2.0.1
Summary: Static scanner and Annex IV drafter for EU AI Act compliance (prototype)
Home-page: https://github.com/svel26/ai-act-check
Author: AnnexFour
Author-email: noreply@annexfour.com
License: AGPL-3.0
Project-URL: Source, https://github.com/svel26/ai-act-check
Project-URL: Homepage, https://annexfour.com
Classifier: Development Status :: 4 - Beta
Classifier: Intended Audience :: Developers
Classifier: License :: OSI Approved :: Apache Software License
Classifier: Programming Language :: Python :: 3
Classifier: Programming Language :: Python :: 3.8
Classifier: Programming Language :: Python :: 3.9
Classifier: Programming Language :: Python :: 3.10
Classifier: Programming Language :: Python :: 3.11
Classifier: Topic :: Software Development :: Quality Assurance
Requires-Python: >=3.8
License-File: LICENSE
Requires-Dist: python-dotenv>=0.19.0
Requires-Dist: openai>=0.27.0
Requires-Dist: requests>=2.25.0
Dynamic: author
Dynamic: author-email
Dynamic: classifier
Dynamic: description
Dynamic: description-content-type
Dynamic: home-page
Dynamic: license
Dynamic: license-file
Dynamic: project-url
Dynamic: requires-dist
Dynamic: requires-python
Dynamic: summary
